CodernityDB/__init__.py
CodernityDB/database.py
CodernityDB/database_gevent.py
CodernityDB/database_safe_shared.py
CodernityDB/database_super_thread_safe.py
CodernityDB/database_thread_safe.py
CodernityDB/debug_stuff.py
CodernityDB/env.py
CodernityDB/hash_index.py
CodernityDB/index.py
CodernityDB/indexcreator.py
CodernityDB/lfu_cache.py
CodernityDB/lfu_cache_with_lock.py
CodernityDB/migrate.py
CodernityDB/misc.py
CodernityDB/patch.py
CodernityDB/rr_cache.py
CodernityDB/rr_cache_with_lock.py
CodernityDB/sharded_hash.py
CodernityDB/sharded_index.py
CodernityDB/storage.py
CodernityDB/tree_index.py
CodernityDB3/__init__.py
CodernityDB3/database.py
CodernityDB3/database_gevent.py
CodernityDB3/database_safe_shared.py
CodernityDB3/database_super_thread_safe.py
CodernityDB3/database_thread_safe.py
CodernityDB3/debug_stuff.py
CodernityDB3/env.py
CodernityDB3/hash_index.py
CodernityDB3/index.py
CodernityDB3/indexcreator.py
CodernityDB3/lfu_cache.py
CodernityDB3/lfu_cache_with_lock.py
CodernityDB3/migrate.py
CodernityDB3/misc.py
CodernityDB3/patch.py
CodernityDB3/rr_cache.py
CodernityDB3/rr_cache_with_lock.py
CodernityDB3/sharded_hash.py
CodernityDB3/sharded_index.py
CodernityDB3/storage.py
CodernityDB3/tree_index.py
access/__init__.py
access/key_ring.py
access/shared_access_coordinator.py
access/shared_access_donor.py
automats/__init__.py
automats/automat.py
automats/global_state.py
blockchain/__init__.py
broadcast/__init__.py
broadcast/broadcast_listener.py
broadcast/broadcast_service.py
broadcast/broadcaster_node.py
broadcast/broadcasters_finder.py
chat/__init__.py
chat/history.py
chat/kbhit.py
chat/message.py
chat/message_db.py
chat/message_index.py
chat/message_keeper.py
chat/message_subscriber.py
chat/message_transmitter.py
chat/nickname_holder.py
chat/nickname_observer.py
chat/terminal_chat.py
coins/__init__.py
coins/accountant_node.py
coins/accountants_finder.py
coins/coins_db.py
coins/coins_index.py
coins/coins_io.py
coins/coins_miner.py
bitdust-0.0.2.dist-info/LICENSE.txt
bitdust-0.0.2.dist-info/METADATA
bitdust-0.0.2.dist-info/WHEEL
bitdust-0.0.2.dist-info/top_level.txt
bitdust-0.0.2.dist-info/RECORD
