Metadata-Version: 2.1
Name: bitdust
Version: 0.0.2
Summary: BitDust is a decentralized on-line storage network for safe, independent and private communications.
Home-page: https://github.com/bitdust-io/public.git
Author: Veselin Penev
Author-email: bitdust.io@gmail.com
License: GNU Affero General Public License v3 or later (AGPLv3+)
Platform: UNKNOWN
Classifier: Development Status :: 3 - Alpha
Classifier: Environment :: Console
Classifier: Environment :: No Input/Output (Daemon)
Classifier: Framework :: Twisted
Classifier: Intended Audience :: Developers
Classifier: Intended Audience :: End Users/Desktop
Classifier: Intended Audience :: Information Technology
Classifier: Intended Audience :: Science/Research
Classifier: Intended Audience :: Telecommunications Industry
Classifier: License :: OSI Approved :: GNU Affero General Public License v3 or later (AGPLv3+)
Classifier: Natural Language :: English
Classifier: Operating System :: OS Independent
Classifier: Programming Language :: Python
Classifier: Programming Language :: Python :: 2
Classifier: Programming Language :: Python :: 2.7
Classifier: Programming Language :: Python :: 3
Classifier: Programming Language :: Python :: 3.6
Classifier: Topic :: Communications :: Chat
Classifier: Topic :: Internet :: WWW/HTTP
Classifier: Topic :: Communications :: File Sharing
Classifier: Topic :: Desktop Environment :: File Managers
Classifier: Topic :: Internet :: File Transfer Protocol (FTP)
Classifier: Topic :: Security :: Cryptography
Classifier: Topic :: System :: Archiving :: Backup
Classifier: Topic :: System :: Distributed Computing
Classifier: Topic :: System :: Filesystems
Classifier: Topic :: System :: System Shells
Classifier: Topic :: Utilities
Requires-Dist: twisted (==18.7.0)
Requires-Dist: service-identity
Requires-Dist: pycryptodomex
Requires-Dist: pyparsing
Requires-Dist: appdirs
Requires-Dist: psutil
Requires-Dist: cffi
Requires-Dist: six
